mir/orbis/__init__.py
mir/orbis/__main__.py
mir/orbis/commands.py
mir/orbis/hashcache.py
mir/orbis/indexing.py
mir/orbis/pictus.py
mir.orbis-0.8.0.dist-info/DESCRIPTION.rst
mir.orbis-0.8.0.dist-info/METADATA
mir.orbis-0.8.0.dist-info/RECORD
mir.orbis-0.8.0.dist-info/WHEEL
mir.orbis-0.8.0.dist-info/metadata.json
mir.orbis-0.8.0.dist-info/top_level.txt
