Metadata-Version: 2.0
Name: mir.orbis
Version: 0.8.0
Summary: Hashed file archives
Home-page: https://github.com/darkfeline/mir.orbis
Author: Allen Li
Author-email: darkfeline@felesatra.moe
License: UNKNOWN
Platform: UNKNOWN
Classifier: Development Status :: 3 - Alpha
Classifier: Intended Audience :: End Users/Desktop
Classifier: License :: OSI Approved :: Apache Software License
Classifier: Programming Language :: Python :: 3.6
Requires-Dist: mir.xdg (~=1.0)
